<DATAMODEL name="businesslog" xmlns:xsi="http://www.w3.org/2001/XMLSchema-instance" xsi:noNamespaceSchemaLocation="datamodel.xsd">
			<NODE name="idBusinessLog" type="int" nullable="false" autoincrement="true" lenght="11"/>
    		<NODE name="idContact" type="int" nullable="false" autoincrement="false" lenght="11"/>
    		<NODE name="idBusinessUnit" type="int" nullable="false" autoincrement="false" lenght="11"/>
    		<NODE name="logDate" type="datetime" nullable="false" autoincrement="false" lenght="19"/>
    		<NODE name="keyName" type="string" nullable="true" autoincrement="false" lenght="45"/>
    		<NODE name="subKeyName" type="string" nullable="true" autoincrement="false" lenght="45"/>
    		<NODE name="message" type="string" nullable="true" autoincrement="false" lenght="1000"/>
    		<NODE name="sessionId" type="string" nullable="false" autoincrement="false" lenght="255"/>
    </DATAMODEL>
