<DATAMODEL name="tariff" xmlns:xsi="http://www.w3.org/2001/XMLSchema-instance" xsi:noNamespaceSchemaLocation="datamodel.xsd">
			<NODE name="idBusinessUnit" type="int" nullable="false" autoincrement="false" lenght="11"/>
    		<NODE name="idActionTarget" type="int" nullable="false" autoincrement="false" lenght="11"/>
    		<NODE name="contractCode" type="string" nullable="false" autoincrement="false" lenght="10"/>
    		<NODE name="validityFrom" type="datetime" nullable="false" autoincrement="false" lenght="19"/>
    		<NODE name="validityTo" type="datetime" nullable="true" autoincrement="false" lenght="19"/>
    		<NODE name="description" type="string" nullable="true" autoincrement="false" lenght="255"/>
    		<NODE name="unitType" type="int" nullable="true" autoincrement="false" lenght="11"/>
    		<NODE name="invoicableAmount" type="string" nullable="true" autoincrement="false" lenght="10"/>
    		<NODE name="invoicablePriceType" type="int" nullable="true" autoincrement="false" lenght="11"/>
    		<NODE name="invoicableAccount1Def1" type="string" nullable="true" autoincrement="false" lenght="20"/>
    		<NODE name="invoicableAccount2Def1" type="string" nullable="true" autoincrement="false" lenght="20"/>
    		<NODE name="invoicableRepartition1" type="string" nullable="true" autoincrement="false" lenght="10"/>
    		<NODE name="invoicableAccount1Def2" type="string" nullable="true" autoincrement="false" lenght="20"/>
    		<NODE name="invoicableAccount2Def2" type="string" nullable="true" autoincrement="false" lenght="20"/>
    		<NODE name="invoicableRepartition2" type="string" nullable="true" autoincrement="false" lenght="10"/>
    		<NODE name="internalCostAmount" type="string" nullable="true" autoincrement="false" lenght="10"/>
    		<NODE name="internalCostPriceType" type="int" nullable="true" autoincrement="false" lenght="11"/>
    		<NODE name="internalCostAccount1Def1" type="string" nullable="true" autoincrement="false" lenght="20"/>
    		<NODE name="internalCostAccount2Def1" type="string" nullable="true" autoincrement="false" lenght="20"/>
    		<NODE name="internalCostRepartition1" type="string" nullable="true" autoincrement="false" lenght="10"/>
    		<NODE name="internalCostAccount1Def2" type="string" nullable="true" autoincrement="false" lenght="20"/>
    		<NODE name="internalCostAccount2Def2" type="string" nullable="true" autoincrement="false" lenght="20"/>
    		<NODE name="internalCostRepartition2" type="string" nullable="true" autoincrement="false" lenght="10"/>
    </DATAMODEL>
